framework/__init__.py
framework/__pycache__/__init__.cpython-38.pyc
framework/constants/__init__.py
framework/constants/commonconfigenum.py
framework/constants/persistencevolumeenum.py
framework/constants/submissionenum.py
framework/constants/__pycache__/__init__.cpython-38.pyc
framework/constants/__pycache__/commonconfigenum.cpython-38.pyc
framework/constants/__pycache__/persistencevolumeenum.cpython-38.pyc
framework/constants/__pycache__/submissionenum.cpython-38.pyc
framework/utils/__init__.py
framework/utils/app_enums.py.notused
framework/utils/attachment.py.notused
framework/utils/confluent_kafka_producer.py.notused
framework/utils/cosutils.py
framework/utils/cosutilsOld.py.notused
framework/utils/db2utils.py
framework/utils/watson_nlu_utils.py.notused
framework/utils/watsondiscoveryutils.py
framework/utils/watsondiscoveryutilsv2.py
framework/utils/__pycache__/__init__.cpython-38.pyc
framework/utils/__pycache__/cosutils.cpython-38.pyc
framework/utils/__pycache__/db2utils.cpython-38.pyc
framework/utils/__pycache__/watsondiscoveryutils.cpython-38.pyc
aw_bizai_framework-0.0.9.dist-info/METADATA
aw_bizai_framework-0.0.9.dist-info/WHEEL
aw_bizai_framework-0.0.9.dist-info/top_level.txt
aw_bizai_framework-0.0.9.dist-info/RECORD
