Metadata-Version: 2.1
Name: aw-bizai-framework
Version: 0.0.9
Summary: BizAI Framework Package
Home-page: UNKNOWN
Author: Arun Wagle
Author-email: arun.wagle@gmail.com
License: GPL
Platform: UNKNOWN
Requires-Python: >=3.6
